{
  "updated_at": "2025-12-08T00:15:00Z",
  "network": "NEM",
  "summary": {
    "net_generation_mw": 30009.8,
    "renewables_mw": 21581.5,
    "renewables_pct": 71.9,
    "demand_mw": 16580.7
  },
  "generation": [
    {
      "fueltech": "battery",
      "label": "battery",
      "power_mw": -762.7,
      "proportion_pct": -2.5,
      "price_dollar_per_mwh": null,
      "total_energy_mwh": -63.6
    },
    {
      "fueltech": "battery_discharging",
      "label": "Battery (Discharging)",
      "power_mw": 8.5,
      "proportion_pct": 0,
      "price_dollar_per_mwh": -8.8,
      "total_energy_mwh": 0.7
    },
    {
      "fueltech": "bioenergy_biomass",
      "label": "Bioenergy (Biomass)",
      "power_mw": 7.9,
      "proportion_pct": 0,
      "price_dollar_per_mwh": 0,
      "total_energy_mwh": 0.7
    },
    {
      "fueltech": "coal_black",
      "label": "Coal (Black)",
      "power_mw": 5823.7,
      "proportion_pct": 19.4,
      "price_dollar_per_mwh": 0,
      "total_energy_mwh": 485.3
    },
    {
      "fueltech": "distillate",
      "label": "Distillate",
      "power_mw": -0.1,
      "proportion_pct": 0,
      "price_dollar_per_mwh": null,
      "total_energy_mwh": 0
    },
    {
      "fueltech": "gas_ccgt",
      "label": "Gas (CCGT)",
      "power_mw": 119.6,
      "proportion_pct": 0.4,
      "price_dollar_per_mwh": 0,
      "total_energy_mwh": 10
    },
    {
      "fueltech": "gas_ocgt",
      "label": "Gas (OCGT)",
      "power_mw": 78.2,
      "proportion_pct": 0.3,
      "price_dollar_per_mwh": -4.88,
      "total_energy_mwh": 6.5
    },
    {
      "fueltech": "hydro",
      "label": "Hydro",
      "power_mw": 484.7,
      "proportion_pct": 1.6,
      "price_dollar_per_mwh": 51.4,
      "total_energy_mwh": 40.4
    },
    {
      "fueltech": "solar_rooftop",
      "label": "Solar (Rooftop)",
      "power_mw": 11597.4,
      "proportion_pct": 38.6,
      "price_dollar_per_mwh": -3.43,
      "total_energy_mwh": 966.5
    },
    {
      "fueltech": "solar_utility",
      "label": "Solar (Utility)",
      "power_mw": 6963.2,
      "proportion_pct": 23.2,
      "price_dollar_per_mwh": -1.07,
      "total_energy_mwh": 580.3
    },
    {
      "fueltech": "wind",
      "label": "Wind",
      "power_mw": 2519.7,
      "proportion_pct": 8.4,
      "price_dollar_per_mwh": 2.45,
      "total_energy_mwh": 210
    },
    {
      "fueltech": "gas_wcmg",
      "label": "Gas (Waste Coal Mine)",
      "power_mw": 43.9,
      "proportion_pct": 0.1,
      "price_dollar_per_mwh": 0,
      "total_energy_mwh": 3.7
    },
    {
      "fueltech": "gas_recip",
      "label": "Gas (Reciprocating)",
      "power_mw": 0,
      "proportion_pct": 0,
      "price_dollar_per_mwh": null,
      "total_energy_mwh": 0
    },
    {
      "fueltech": "gas_steam",
      "label": "Gas (Steam)",
      "power_mw": 41,
      "proportion_pct": 0.1,
      "price_dollar_per_mwh": -9.5,
      "total_energy_mwh": 3.4
    },
    {
      "fueltech": "coal_brown",
      "label": "Coal (Brown)",
      "power_mw": 2321.8,
      "proportion_pct": 7.7,
      "price_dollar_per_mwh": -10.35,
      "total_energy_mwh": 193.5
    }
  ],
  "loads": [
    {
      "fueltech": "battery_charging",
      "label": "Battery (Charging)",
      "power_mw": 771.3,
      "proportion_pct": 2.6,
      "price_dollar_per_mwh": -5.12,
      "total_energy_mwh": 64.3
    },
    {
      "fueltech": "pumps",
      "label": "Pumps",
      "power_mw": 483,
      "proportion_pct": 1.6,
      "price_dollar_per_mwh": 0,
      "total_energy_mwh": 40.3
    }
  ],
  "curtailment": [
    {
      "fueltech": "solar_utility",
      "label": "Solar (Utility)",
      "power_mw": 2220.2,
      "proportion_pct": 7.4
    },
    {
      "fueltech": "wind",
      "label": "Wind",
      "power_mw": 1631.9,
      "proportion_pct": 5.4
    }
  ],
  "emissions": {
    "volume_tco2e_per_30m": 679.4,
    "intensity_kgco2e_per_mwh": 271.65
  },
  "regions": {
    "NSW1": {
      "price_dollar_per_mwh": 0,
      "demand_mw": 6273.2,
      "summary": {
        "net_generation_mw": 9819.2,
        "renewables_mw": 7637.9,
        "renewables_pct": 77.8,
        "demand_mw": 6273.2
      },
      "generation": [
        {
          "fueltech": "battery",
          "label": "battery",
          "power_mw": -38.2,
          "proportion_pct": -0.4,
          "price_dollar_per_mwh": null,
          "total_energy_mwh": -3.2
        },
        {
          "fueltech": "battery_discharging",
          "label": "Battery (Discharging)",
          "power_mw": 0.2,
          "proportion_pct": 0,
          "price_dollar_per_mwh": 0,
          "total_energy_mwh": 0
        },
        {
          "fueltech": "bioenergy_biomass",
          "label": "Bioenergy (Biomass)",
          "power_mw": 10.1,
          "proportion_pct": 0.1,
          "price_dollar_per_mwh": 0,
          "total_energy_mwh": 0.8
        },
        {
          "fueltech": "coal_black",
          "label": "Coal (Black)",
          "power_mw": 2143.5,
          "proportion_pct": 21.8,
          "price_dollar_per_mwh": 0,
          "total_energy_mwh": 178.6
        },
        {
          "fueltech": "distillate",
          "label": "Distillate",
          "power_mw": 0,
          "proportion_pct": 0,
          "price_dollar_per_mwh": null,
          "total_energy_mwh": 0
        },
        {
          "fueltech": "gas_ccgt",
          "label": "Gas (CCGT)",
          "power_mw": 0,
          "proportion_pct": 0,
          "price_dollar_per_mwh": null,
          "total_energy_mwh": 0
        },
        {
          "fueltech": "gas_ocgt",
          "label": "Gas (OCGT)",
          "power_mw": 37.8,
          "proportion_pct": 0.4,
          "price_dollar_per_mwh": 0,
          "total_energy_mwh": 3.2
        },
        {
          "fueltech": "hydro",
          "label": "Hydro",
          "power_mw": 18.5,
          "proportion_pct": 0.2,
          "price_dollar_per_mwh": 0,
          "total_energy_mwh": 1.5
        },
        {
          "fueltech": "solar_rooftop",
          "label": "Solar (Rooftop)",
          "power_mw": 3852.1,
          "proportion_pct": 39.2,
          "price_dollar_per_mwh": 0,
          "total_energy_mwh": 321
        },
        {
          "fueltech": "solar_utility",
          "label": "Solar (Utility)",
          "power_mw": 3305.9,
          "proportion_pct": 33.7,
          "price_dollar_per_mwh": 0,
          "total_energy_mwh": 275.5
        },
        {
          "fueltech": "wind",
          "label": "Wind",
          "power_mw": 451,
          "proportion_pct": 4.6,
          "price_dollar_per_mwh": 0,
          "total_energy_mwh": 37.6
        }
      ],
      "loads": [
        {
          "fueltech": "battery_charging",
          "label": "Battery (Charging)",
          "power_mw": 38.4,
          "proportion_pct": 0.4,
          "price_dollar_per_mwh": 0,
          "total_energy_mwh": 3.2
        },
        {
          "fueltech": "pumps",
          "label": "Pumps",
          "power_mw": 240.1,
          "proportion_pct": 2.4,
          "price_dollar_per_mwh": 0,
          "total_energy_mwh": 20
        }
      ],
      "curtailment": [
        {
          "fueltech": "solar_utility",
          "label": "Solar (Utility)",
          "power_mw": 891.8,
          "proportion_pct": 9.1
        },
        {
          "fueltech": "wind",
          "label": "Wind",
          "power_mw": 0,
          "proportion_pct": 0
        }
      ],
      "emissions": {
        "volume_tco2e_per_30m": 162.2,
        "intensity_kgco2e_per_mwh": 198.17
      }
    },
    "QLD1": {
      "price_dollar_per_mwh": 0,
      "demand_mw": 5796.9,
      "summary": {
        "net_generation_mw": 10014.5,
        "renewables_mw": 6168.3,
        "renewables_pct": 61.6,
        "demand_mw": 5796.9
      },
      "generation": [
        {
          "fueltech": "battery",
          "label": "battery",
          "power_mw": -350.6,
          "proportion_pct": -3.5,
          "price_dollar_per_mwh": null,
          "total_energy_mwh": -29.2
        },
        {
          "fueltech": "battery_discharging",
          "label": "Battery (Discharging)",
          "power_mw": 1,
          "proportion_pct": 0,
          "price_dollar_per_mwh": 0,
          "total_energy_mwh": 0.1
        },
        {
          "fueltech": "bioenergy_biomass",
          "label": "Bioenergy (Biomass)",
          "power_mw": -2.2,
          "proportion_pct": 0,
          "price_dollar_per_mwh": null,
          "total_energy_mwh": -0.2
        },
        {
          "fueltech": "coal_black",
          "label": "Coal (Black)",
          "power_mw": 3680.2,
          "proportion_pct": 36.7,
          "price_dollar_per_mwh": 0,
          "total_energy_mwh": 306.7
        },
        {
          "fueltech": "distillate",
          "label": "Distillate",
          "power_mw": 0,
          "proportion_pct": 0,
          "price_dollar_per_mwh": null,
          "total_energy_mwh": 0
        },
        {
          "fueltech": "gas_ccgt",
          "label": "Gas (CCGT)",
          "power_mw": 119.6,
          "proportion_pct": 1.2,
          "price_dollar_per_mwh": 0,
          "total_energy_mwh": 10
        },
        {
          "fueltech": "gas_ocgt",
          "label": "Gas (OCGT)",
          "power_mw": 0.3,
          "proportion_pct": 0,
          "price_dollar_per_mwh": 0,
          "total_energy_mwh": 0
        },
        {
          "fueltech": "gas_wcmg",
          "label": "Gas (Waste Coal Mine)",
          "power_mw": 43.9,
          "proportion_pct": 0.4,
          "price_dollar_per_mwh": 0,
          "total_energy_mwh": 3.7
        },
        {
          "fueltech": "hydro",
          "label": "Hydro",
          "power_mw": 4.8,
          "proportion_pct": 0,
          "price_dollar_per_mwh": 0,
          "total_energy_mwh": 0.4
        },
        {
          "fueltech": "solar_rooftop",
          "label": "Solar (Rooftop)",
          "power_mw": 3115.2,
          "proportion_pct": 31.1,
          "price_dollar_per_mwh": 0,
          "total_energy_mwh": 259.6
        },
        {
          "fueltech": "solar_utility",
          "label": "Solar (Utility)",
          "power_mw": 2930.9,
          "proportion_pct": 29.3,
          "price_dollar_per_mwh": 0,
          "total_energy_mwh": 244.2
        },
        {
          "fueltech": "wind",
          "label": "Wind",
          "power_mw": 118.6,
          "proportion_pct": 1.2,
          "price_dollar_per_mwh": 0,
          "total_energy_mwh": 9.9
        }
      ],
      "loads": [
        {
          "fueltech": "battery_charging",
          "label": "Battery (Charging)",
          "power_mw": 351.7,
          "proportion_pct": 3.5,
          "price_dollar_per_mwh": 0,
          "total_energy_mwh": 29.3
        },
        {
          "fueltech": "pumps",
          "label": "Pumps",
          "power_mw": 242.9,
          "proportion_pct": 2.4,
          "price_dollar_per_mwh": 0,
          "total_energy_mwh": 20.2
        }
      ],
      "curtailment": [
        {
          "fueltech": "solar_utility",
          "label": "Solar (Utility)",
          "power_mw": 261.8,
          "proportion_pct": 2.6
        },
        {
          "fueltech": "wind",
          "label": "Wind",
          "power_mw": 11.7,
          "proportion_pct": 0.1
        }
      ],
      "emissions": {
        "volume_tco2e_per_30m": 279.3,
        "intensity_kgco2e_per_mwh": 334.72
      }
    },
    "SA1": {
      "price_dollar_per_mwh": -9.5,
      "demand_mw": 304,
      "summary": {
        "net_generation_mw": 1970.2,
        "renewables_mw": 1888.4,
        "renewables_pct": 95.8,
        "demand_mw": 304
      },
      "generation": [
        {
          "fueltech": "battery",
          "label": "battery",
          "power_mw": 0.7,
          "proportion_pct": 0,
          "price_dollar_per_mwh": -12.39,
          "total_energy_mwh": 0.1
        },
        {
          "fueltech": "battery_discharging",
          "label": "Battery (Discharging)",
          "power_mw": 0.9,
          "proportion_pct": 0,
          "price_dollar_per_mwh": -9.5,
          "total_energy_mwh": 0.1
        },
        {
          "fueltech": "distillate",
          "label": "Distillate",
          "power_mw": -0.1,
          "proportion_pct": 0,
          "price_dollar_per_mwh": null,
          "total_energy_mwh": 0
        },
        {
          "fueltech": "gas_ccgt",
          "label": "Gas (CCGT)",
          "power_mw": 0,
          "proportion_pct": 0,
          "price_dollar_per_mwh": null,
          "total_energy_mwh": 0
        },
        {
          "fueltech": "gas_ocgt",
          "label": "Gas (OCGT)",
          "power_mw": 40.1,
          "proportion_pct": 2,
          "price_dollar_per_mwh": -9.5,
          "total_energy_mwh": 3.3
        },
        {
          "fueltech": "gas_recip",
          "label": "Gas (Reciprocating)",
          "power_mw": 0,
          "proportion_pct": 0,
          "price_dollar_per_mwh": null,
          "total_energy_mwh": 0
        },
        {
          "fueltech": "gas_steam",
          "label": "Gas (Steam)",
          "power_mw": 41,
          "proportion_pct": 2.1,
          "price_dollar_per_mwh": -9.5,
          "total_energy_mwh": 3.4
        },
        {
          "fueltech": "solar_rooftop",
          "label": "Solar (Rooftop)",
          "power_mw": 1622,
          "proportion_pct": 82.3,
          "price_dollar_per_mwh": -9.5,
          "total_energy_mwh": 135.2
        },
        {
          "fueltech": "solar_utility",
          "label": "Solar (Utility)",
          "power_mw": 65.5,
          "proportion_pct": 3.3,
          "price_dollar_per_mwh": -9.5,
          "total_energy_mwh": 5.5
        },
        {
          "fueltech": "wind",
          "label": "Wind",
          "power_mw": 200,
          "proportion_pct": 10.2,
          "price_dollar_per_mwh": -9.5,
          "total_energy_mwh": 16.7
        }
      ],
      "loads": [
        {
          "fueltech": "battery_charging",
          "label": "Battery (Charging)",
          "power_mw": 0.2,
          "proportion_pct": 0,
          "price_dollar_per_mwh": -9.51,
          "total_energy_mwh": 0
        }
      ],
      "curtailment": [
        {
          "fueltech": "solar_utility",
          "label": "Solar (Utility)",
          "power_mw": 497.7,
          "proportion_pct": 25.3
        },
        {
          "fueltech": "wind",
          "label": "Wind",
          "power_mw": 310.9,
          "proportion_pct": 15.8
        }
      ],
      "emissions": {
        "volume_tco2e_per_30m": 4.8,
        "intensity_kgco2e_per_mwh": 29.48
      }
    },
    "TAS1": {
      "price_dollar_per_mwh": 54.17,
      "demand_mw": 1050.9,
      "summary": {
        "net_generation_mw": 971,
        "renewables_mw": 971,
        "renewables_pct": 100,
        "demand_mw": 1050.9
      },
      "generation": [
        {
          "fueltech": "gas_ccgt",
          "label": "Gas (CCGT)",
          "power_mw": 0,
          "proportion_pct": 0,
          "price_dollar_per_mwh": null,
          "total_energy_mwh": 0
        },
        {
          "fueltech": "gas_ocgt",
          "label": "Gas (OCGT)",
          "power_mw": 0,
          "proportion_pct": 0,
          "price_dollar_per_mwh": null,
          "total_energy_mwh": 0
        },
        {
          "fueltech": "hydro",
          "label": "Hydro",
          "power_mw": 460.2,
          "proportion_pct": 47.4,
          "price_dollar_per_mwh": 54.17,
          "total_energy_mwh": 38.3
        },
        {
          "fueltech": "solar_rooftop",
          "label": "Solar (Rooftop)",
          "power_mw": 104.8,
          "proportion_pct": 10.8,
          "price_dollar_per_mwh": 54.17,
          "total_energy_mwh": 8.7
        },
        {
          "fueltech": "wind",
          "label": "Wind",
          "power_mw": 406,
          "proportion_pct": 41.8,
          "price_dollar_per_mwh": 54.17,
          "total_energy_mwh": 33.8
        }
      ],
      "loads": [],
      "curtailment": [
        {
          "fueltech": "solar_utility",
          "label": "Solar (Utility)",
          "power_mw": 0,
          "proportion_pct": 0
        },
        {
          "fueltech": "wind",
          "label": "Wind",
          "power_mw": 0,
          "proportion_pct": 0
        }
      ],
      "emissions": {
        "volume_tco2e_per_30m": 0,
        "intensity_kgco2e_per_mwh": 0
      }
    },
    "VIC1": {
      "price_dollar_per_mwh": -10.35,
      "demand_mw": 3155.8,
      "summary": {
        "net_generation_mw": 7237.7,
        "renewables_mw": 4915.9,
        "renewables_pct": 67.9,
        "demand_mw": 3155.8
      },
      "generation": [
        {
          "fueltech": "battery",
          "label": "battery",
          "power_mw": -374.5,
          "proportion_pct": -5.2,
          "price_dollar_per_mwh": null,
          "total_energy_mwh": -31.2
        },
        {
          "fueltech": "battery_discharging",
          "label": "Battery (Discharging)",
          "power_mw": 6.5,
          "proportion_pct": 0.1,
          "price_dollar_per_mwh": -10.35,
          "total_energy_mwh": 0.5
        },
        {
          "fueltech": "coal_brown",
          "label": "Coal (Brown)",
          "power_mw": 2321.8,
          "proportion_pct": 32.1,
          "price_dollar_per_mwh": -10.35,
          "total_energy_mwh": 193.5
        },
        {
          "fueltech": "gas_ocgt",
          "label": "Gas (OCGT)",
          "power_mw": 0,
          "proportion_pct": 0,
          "price_dollar_per_mwh": null,
          "total_energy_mwh": 0
        },
        {
          "fueltech": "gas_steam",
          "label": "Gas (Steam)",
          "power_mw": 0,
          "proportion_pct": 0,
          "price_dollar_per_mwh": null,
          "total_energy_mwh": 0
        },
        {
          "fueltech": "hydro",
          "label": "Hydro",
          "power_mw": 1.2,
          "proportion_pct": 0,
          "price_dollar_per_mwh": -10.35,
          "total_energy_mwh": 0.1
        },
        {
          "fueltech": "solar_rooftop",
          "label": "Solar (Rooftop)",
          "power_mw": 2903.2,
          "proportion_pct": 40.1,
          "price_dollar_per_mwh": -10.35,
          "total_energy_mwh": 241.9
        },
        {
          "fueltech": "solar_utility",
          "label": "Solar (Utility)",
          "power_mw": 660.9,
          "proportion_pct": 9.1,
          "price_dollar_per_mwh": -10.35,
          "total_energy_mwh": 55.1
        },
        {
          "fueltech": "wind",
          "label": "Wind",
          "power_mw": 1344,
          "proportion_pct": 18.6,
          "price_dollar_per_mwh": -10.35,
          "total_energy_mwh": 112
        }
      ],
      "loads": [
        {
          "fueltech": "battery_charging",
          "label": "Battery (Charging)",
          "power_mw": 381,
          "proportion_pct": 5.3,
          "price_dollar_per_mwh": -10.35,
          "total_energy_mwh": 31.8
        }
      ],
      "curtailment": [
        {
          "fueltech": "solar_utility",
          "label": "Solar (Utility)",
          "power_mw": 568.9,
          "proportion_pct": 7.9
        },
        {
          "fueltech": "wind",
          "label": "Wind",
          "power_mw": 1309.3,
          "proportion_pct": 18.1
        }
      ],
      "emissions": {
        "volume_tco2e_per_30m": 233.1,
        "intensity_kgco2e_per_mwh": 386.43
      }
    },
    "WEM": {
      "price_dollar_per_mwh": null,
      "demand_mw": null,
      "summary": {
        "net_generation_mw": 0,
        "renewables_mw": 0,
        "renewables_pct": null,
        "demand_mw": null
      },
      "generation": [],
      "loads": [],
      "curtailment": [
        {
          "fueltech": "solar_utility",
          "label": "Solar (Utility)",
          "power_mw": 0,
          "proportion_pct": null
        },
        {
          "fueltech": "wind",
          "label": "Wind",
          "power_mw": 0,
          "proportion_pct": null
        }
      ],
      "emissions": {
        "volume_tco2e_per_30m": 0,
        "intensity_kgco2e_per_mwh": null
      }
    }
  }
}
